{
  "campaign_id": "knowledge-narrative-depth-wave-2b-events-timelines-2026-07",
  "page_id": "KNOW-236C89C5E44E7989",
  "proposed_path": "knowledge/events/Event-Evidence-Registry.md",
  "page_action": "EXPAND_AND_STANDARDIZE",
  "proposed_knowledge_status": "QUALIFIED",
  "page_risk_score": 5,
  "page_risk_class": "R2",
  "subject_entities": [],
  "aliases": [],
  "scope": "Event identity and evidence stages remain distinct.",
  "material_claims": [],
  "known_limitations": [
    "Material chronology remains governed by citations and limitations in the page."
  ],
  "research_gaps": [
    "See the page's open chronology questions and research-gaps metadata."
  ],
  "review_required": true,
  "review_after": "2027-01-20"
}
